charfinder/__init__.py
charfinder/__main__.py
charfinder/fuzzymatchlib.py
charfinder/py.typed
charfinder/validators.py
charfinder/cli/__init__.py
charfinder/cli/args.py
charfinder/cli/cli_main.py
charfinder/cli/diagnostics.py
charfinder/cli/diagnostics_match.py
charfinder/cli/handlers.py
charfinder/cli/parser.py
charfinder/cli/utils_runner.py
charfinder/config/__init__.py
charfinder/config/aliases.py
charfinder/config/constants.py
charfinder/config/messages.py
charfinder/config/settings.py
charfinder/config/types.py
charfinder/core/__init__.py
charfinder/core/core_main.py
charfinder/core/finders.py
charfinder/core/handlers.py
charfinder/core/matching.py
charfinder/core/name_cache.py
charfinder/core/unicode_data_loader.py
charfinder/utils/__init__.py
charfinder/utils/formatter.py
charfinder/utils/logger_helpers.py
charfinder/utils/logger_setup.py
charfinder/utils/logger_styles.py
charfinder/utils/normalizer.py
charfinder-1.1.9.dist-info/licenses/LICENSE.txt
charfinder-1.1.9.dist-info/METADATA
charfinder-1.1.9.dist-info/WHEEL
charfinder-1.1.9.dist-info/entry_points.txt
charfinder-1.1.9.dist-info/top_level.txt
charfinder-1.1.9.dist-info/RECORD
