Metadata-Version: 2.4
Name: charfinder
Version: 1.1.9
Summary: A CLI and library for normalized Unicode character search with fuzzy matching.
Author-email: Hamed VAHEB <hamed.vaheb@protonmail.com>
License: MIT
Project-URL: Homepage, https://github.com/berserkhmdvhb/charfinder
Project-URL: Source, https://github.com/berserkhmdvhb/charfinder
Project-URL: Issues, https://github.com/berserkhmdvhb/charfinder/issues
Project-URL: Changelog, https://github.com/berserkhmdvhb/charfinder/releases
Project-URL: CI, https://github.com/berserkhmdvhb/charfinder/actions
Keywords: unicode,cli,fuzzy,search,character,text
Classifier: Environment :: Console
Classifier: Intended Audience :: Developers
Classifier: Topic :: Text Processing
Classifier: Topic :: Utilities
Classifier: License :: OSI Approved :: MIT License
Classifier: Operating System :: OS Independent
Classifier: Typing :: Typed
Classifier: Programming Language :: Python :: 3
Classifier: Programming Language :: Python :: 3.10
Classifier: Programming Language :: Python :: 3.11
Classifier: Programming Language :: Python :: 3.12
Classifier: Programming Language :: Python :: 3.13
Requires-Python: >=3.10
License-File: LICENSE.txt
Requires-Dist: argcomplete>=3.1.0
Requires-Dist: colorama>=0.4.0
Requires-Dist: Levenshtein>=0.27.1
Requires-Dist: python-dotenv>=1.0
Requires-Dist: RapidFuzz>=3.13.0
Requires-Dist: typing_extensions>=4.4.0
Provides-Extra: dev
Requires-Dist: build; extra == "dev"
Requires-Dist: coverage==7.5.0; extra == "dev"
Requires-Dist: coveralls>=3.3.2; python_version < "3.13" and extra == "dev"
Requires-Dist: mypy; extra == "dev"
Requires-Dist: pre-commit; extra == "dev"
Requires-Dist: pytest; extra == "dev"
Requires-Dist: pytest-cov; extra == "dev"
Requires-Dist: pytest-watch; extra == "dev"
Requires-Dist: ruff; extra == "dev"
Requires-Dist: safety; extra == "dev"
Requires-Dist: twine; extra == "dev"
Requires-Dist: types-colorama; extra == "dev"
Dynamic: license-file
